gelidum/__init__.py
gelidum/decorators.py
gelidum/dependencies.py
gelidum/exceptions.py
gelidum/freeze.py
gelidum/on_freeze.py
gelidum/typing.py
gelidum/utils.py
gelidum/collections/__init__.py
gelidum/collections/frozendict.py
gelidum/collections/frozenlist.py
gelidum/collections/frozenndarray.py
gelidum/collections/frozenzet.py
gelidum/frozen/__init__.py
gelidum/frozen/frozen_base.py
gelidum/frozen/frozen_class_creator.py
gelidum/frozen/isfrozen.py
gelidum/tests/__init__.py
gelidum/tests/test_time_performance.py
gelidum/tests/collection_tests/__init__.py
gelidum/tests/collection_tests/test_frozendict.py
gelidum/tests/collection_tests/test_frozenlist.py
gelidum/tests/collection_tests/test_frozenndarray.py
gelidum/tests/collection_tests/test_frozenzet.py
gelidum/tests/frozen_tests/__init__.py
gelidum/tests/frozen_tests/test_isfrozen.py
gelidum/tests/gelidum_tests/__init__.py
gelidum/tests/gelidum_tests/test_decorators.py
gelidum/tests/gelidum_tests/test_freeze_builtin_objects.py
gelidum/tests/gelidum_tests/test_freeze_dataclasses.py
gelidum/tests/gelidum_tests/test_freeze_functions.py
gelidum/tests/gelidum_tests/test_freeze_modules.py
gelidum/tests/gelidum_tests/test_freeze_numpy_objects.py
gelidum/tests/gelidum_tests/test_freeze_objects.py
gelidum/tests/gelidum_tests/test_freeze_objects_with_self_references.py
gelidum/tests/gelidum_tests/test_on_freeze.py
gelidum/tests/gelidum_tests/utils/__init__.py
gelidum/tests/gelidum_tests/utils/datetime.py
gelidum/tests/gelidum_tests/utils/dummy1.py
gelidum/tests/gelidum_tests/utils/dummy2.py
gelidum-0.10.1.dist-info/licenses/LICENSE
gelidum-0.10.1.dist-info/METADATA
gelidum-0.10.1.dist-info/WHEEL
gelidum-0.10.1.dist-info/top_level.txt
gelidum-0.10.1.dist-info/RECORD
