Metadata-Version: 2.4
Name: gelidum
Version: 0.10.1
Summary: Freeze your objects in python
Author-email: "Diego J. Romero López" <diegojromerolopez@gmail.com>
Project-URL: repository, https://github.com/diegojromerolopez/gelidum
Project-URL: documentation, https://github.com/diegojromerolopez/gelidum/blob/main/README.md
Project-URL: Bug Tracker, https://github.com/diegojromerolopez/gelidum/issues
Keywords: freeze,python,object
Classifier: Programming Language :: Python :: Implementation :: CPython
Classifier: Programming Language :: Python :: Implementation :: PyPy
Classifier: Programming Language :: Python :: 3.9
Classifier: Programming Language :: Python :: 3.10
Classifier: Programming Language :: Python :: 3.11
Classifier: Programming Language :: Python :: 3.12
Classifier: Programming Language :: Python :: 3.13
Classifier: Programming Language :: Python :: 3.14
Classifier: Topic :: Software Development :: Libraries
Classifier: Development Status :: 4 - Beta
Classifier: License :: OSI Approved :: MIT License
Requires-Python: >=3.9
License-File: LICENSE
Dynamic: license-file
